{"dxPwehX4qiNBrLIwOirnqA==":"carloshenriquecord%20(1)-364x364.jpg","U61idWSVctJRLQupZBO/Gw==":"capturar.jpg","1KaZXEsbR1RfrlXWYDDwhg==":"imagem-1920x1080.jpg","5bOf8msVCnnelzuMylXP7g==":"carloshenriquecord%20(3)-506x506.jpg","2emmQD2NiNMNQ86RTRN2EA==":"carloshenriquecord%20(1)-506x506.jpg","BOumqBcRSzBv6c34rSgHhQ==":"carloshenriquecord%20(5)-506x506.jpg","mIIbxW0r7dEZSbMPwcoYdg==":"background2.jpg","e6iRspzJPDNLYyB+VG0Nvw==":"reciso-do-contrato-de-trabalho-por-ato-discriminatrio.jpg","T3Osmn1HT/i7X5cLiUg4GQ==":"renova-conhecimentos-2.jpg","jfDeQmfLEtMHKuB+aMu4RA==":"arte-em-ao.jpg","wY3Ho9nFIlhNrza2LxpPgA==":"curso-teclado.jpg","p0WXO+Z+NwW8yAIToFsSCQ==":"selo6-7dias-0.75x.png","pa5Dkwo/T1qgW/t0h+fQvA==":"background5.jpg","UAc7kepzJPkrSn4uqTRvmw==":"background4.jpg","00zZUyXhpQoaC0uKo25qvA==":"product1.jpg","TME+JuzKvB5rk9PyqOHTog==":"carlos-henrique-cordeiro.jpg","qmhTVKmIz4PibszSSjHsjw==":"capturar-2.jpg","9CBmZEBkCtQqBCLhLprEVw==":"renova-conhecimentos.jpg","seGu5yf3gGSOlorkwS4fNw==":"arte-em-ao-1.jpg","xENCNiq2nB9hiCwtw4/kTw==":"design%20sem%20nome-350x559.jpeg","l1vvj7RHsSCVhTPHeGfsJQ==":"50%20t%C3%89cnicas%20de%20autocoaching-350x350.jpg","hSRHpEB4u4V1F+dPWE8xbg==":"aprenda%20a%20posicionar-se%20nas%20redes%20sociais.%20palestra%20com%20o%20famoso%20roberto%20villareal.%20rua%20do%20porto,%2082%20-%20porto%20velho-ro%2010_12_2020%2020h-350x350.jpg","rCoQ8sAW0lWusq7nOUAy9g==":"aprenda%20a%20posicionar-se%20nas%20redes%20sociais.%20palestra%20com%20o%20famoso%20roberto%20villareal.%20rua%20do%20porto,%2082%20-%20porto%20velho-ro%2010_12_2020%2020h-350x350.jpeg","dfpcYHt1zqap7UrR8mOnLw==":"aprenda%20a%20posicionar-se%20nas%20redes-350x350.jpg","zwZLKTIrQ8DA4G71j+gC8w==":"aprenda%20a%20posicionar-se-350x350.jpg","7BmA9yO/1XIbSQYwybJBSQ==":"aprenda%20a%20posicionar-se%20nas%20redes-350x350.jpg","jg1gtY3qdPuMGrQzI5v2mg==":"aprenda%20a%20posicionar-se-350x350.jpg","H/ivTs8iWw71l+wCk30h5A==":"hamburguer-350x350.jpg","0VD0nNEpRaVbMelWM0XxOg==":"aprenda%20a-350x350.jpg","uAgBQ6t504GhWweL7/jpWA==":"recis%C3%83o%20do%20contrato%20de%20trabalho%20por%20ato%20discriminat%C3%93rio-350x350.jpg","A3QFTIG2eqisUuGvMjNq+Q==":"design%20sem%20nome-350x350.jpg","eEJ1ZNFKOzygRjZO0NNy3g==":"123-350x350.jpg","AupfCno14j4hgBGtJ1JBZw==":"123-506x506.jpg","FQpbGHapmOTZfvwDpQ180g==":"design%20sem%20nome-506x506.jpg","0Qm5rMzUZ+7qs4kSQZxeDA==":"hamburguer-506x506.jpg","Vlqc6MDVKYYkuTdJrxvlYw==":"design%20sem%20nome-506x506.jpg","xe6IK6cs1yIIRwSvcpNsWg==":"curso%20de%20teclado-1-350x495.jpg","kTdKbNnCqZee9BQs6+P4Rw==":"curso%20tecaldo%201-350x559.jpg","Lb5ecLn+QMLwYFyZKxxM0A==":"insta%20gram%20curso%20cavaquinho-350x350.jpg","mLln9mbC1M6y69rlQBf8mg==":"curso%20tecaldo%20atualizado-350x350.jpg","BASZErSoTdCYIOAAVNTu7Q==":"insta%20gram%20curso%20viol%C3%83o-350x350.jpg","NS7pnGknAu9rgiZNx/+x6g==":"renovaconhecimentos-506x506.jpg","aYw34oAP2uvcsnWLNHjFew==":"renovaconhecimentos-1-506x506.jpg","ALithBu4UD636dVhFerO0Q==":"insta%20gram%20curso%20viol%C3%83o-506x506.jpg","hp8ONJ4HGbHQSSZYs1VHqQ==":"insta%20gram%20curso%20cavaquinho-506x506.jpg","L6GdxTeW27uObnL35WyryA==":"artigo%20juridico-506x506.jpg","GrtdraJf3NCr1MEMJ/6JrQ==":"artigo%20juridico-350x350.jpg","MmI48qQ+5KnprUykXcrglw==":"https___renovaconhecimentos.mobirisesite.com_-350x350.jpg","XhfswMhyLq27ciDsCWclmg==":"insta%20gram%20curso%20viol%C3%83o-1016x1016.jpg","CCWeKBycdOSeGtRdXkgZhg==":"insta%20gram%20curso%20cavaquinho-1016x1016.jpg","4k2E5ccRYeXLlw3FEgG57w==":"https___renovaconhecimentos.mobirisesite.com_-1016x1016.jpg"}